{"google":"","body":"<!DOCTYPE html>\r\n<html>\r\n  <head>\r\n\t<title>Просто сайт</title>\r\n\t<style>\r\n   header, nav, section, footer{\r\n\tborder:1px solid black;\r\n }\r\n#wrapper {\r\n\tmargin:0 auto;\r\n\twidth: 95%;\r\n\toutline:1px solid black;\r\n\tpadding: 0 10px 0 10px;\r\n}\r\nheader {\r\n      height:100px;\r\nmargin-bottom: 10px;\r\n}\r\nnav {\r\n\theight: 50px;\r\nmargin-bottom: 10px;\r\n}\r\nsection {\r\n\theight:400px;\r\nmargin-bottom: 10px;\r\n}\r\nfooter {\r\n\theight: 40px;\r\n\tclear:both;\r\n}\r\n#sec1 {\r\n\twidth:20%;\r\n\tfloat:left;\r\n}\r\n#sec2 {\r\n\twidth:20%;\r\n\tfloat:right;\r\n}\r\n#sec3 {\r\n\twidth: 55%;\r\n\tmargin: 0 auto;\r\n}\r\n</style>\r\n  </head>\r\n  <body>\r\n    <div id=\"wrapper\">\r\n\t<header>\r\n\t</header>\r\n\t<nav>\r\n\t\t<a>Home</a>\r\n\t\t<a>About</a>\r\n\t\t<a>News</a>\r\n\t\t<a>Else</a>\r\n\t</nav>\r\n\t<section id=\"sec1\">\r\n\t\t<menu>\r\n\t\t<li>HTML</li>\r\n\t\t<li>CSS</li>\r\n\t\t<li>JS</li>\r\n\t\t<li>PPT</li>\r\n\t\t</menu>\r\n\t</section>\r\n\t<section id=\"sec2\">\r\n\t</section>\r\n\t<section id=\"sec3\">\r\n\t</section>\r\n\t<footer>\r\n\t</footer>\r\n    </div>\r\n  </body>\r\n</html>","name":"My-site шаблон","tagline":"Шаблон","note":"Don't delete this file! It's used internally to help with page regeneration."}